hgraph/__init__.py
hgraph/_builder/__init__.py
hgraph/_builder/_builder.py
hgraph/_builder/_graph_builder.py
hgraph/_builder/_input_builder.py
hgraph/_builder/_node_builder.py
hgraph/_builder/_output_builder.py
hgraph/_builder/_scalar_builder.py
hgraph/_builder/_ts_builder.py
hgraph/_feature_switch.py
hgraph/_hgraph.cp312-win_amd64.pyd
hgraph/_impl/__init__.py
hgraph/_impl/_builder/__init__.py
hgraph/_impl/_builder/_component_builder.py
hgraph/_impl/_builder/_graph_builder.py
hgraph/_impl/_builder/_map_builder.py
hgraph/_impl/_builder/_mesh_builder.py
hgraph/_impl/_builder/_nested_graph_node_builder.py
hgraph/_impl/_builder/_node_builder.py
hgraph/_impl/_builder/_node_impl_builder.py
hgraph/_impl/_builder/_reduce_builder.py
hgraph/_impl/_builder/_service_impl_builder.py
hgraph/_impl/_builder/_switch_builder.py
hgraph/_impl/_builder/_try_except_builder.py
hgraph/_impl/_builder/_ts_builder.py
hgraph/_impl/_impl_configuration.py
hgraph/_impl/_operators/__init__.py
hgraph/_impl/_operators/_bool_operators.py
hgraph/_impl/_operators/_conversion_operators/__init__.py
hgraph/_impl/_operators/_conversion_operators/_compound_scalar_conversion_operators.py
hgraph/_impl/_operators/_conversion_operators/_conversion_operator_util.py
hgraph/_impl/_operators/_conversion_operators/_date_time_conversion_operators.py
hgraph/_impl/_operators/_conversion_operators/_general_conversion_operators.py
hgraph/_impl/_operators/_conversion_operators/_mapping_conversion_operators.py
hgraph/_impl/_operators/_conversion_operators/_set_conversion_operators.py
hgraph/_impl/_operators/_conversion_operators/_to_data_frame_converters.py
hgraph/_impl/_operators/_conversion_operators/_ts_conversion_operators.py
hgraph/_impl/_operators/_conversion_operators/_tsb_conversion_operators.py
hgraph/_impl/_operators/_conversion_operators/_tsd_conversion_operators.py
hgraph/_impl/_operators/_conversion_operators/_tsl_conversion_operators.py
hgraph-0.5.12.dist-info/METADATA
hgraph-0.5.12.dist-info/WHEEL
hgraph-0.5.12.dist-info/entry_points.txt
hgraph-0.5.12.dist-info/licenses/LICENSE
hgraph-0.5.12.dist-info/RECORD
