Metadata-Version: 2.2
Name: hgraph
Version: 0.5.12
Summary: A functional reactive platform used to process time-series streams. Provides support for backtest (simulation) and realtime time-series processing. Using a forward propagation graph with a microtask scheduler for the runtime engine.
Keywords: reactive,graph,fpg,forward propogating graph,time series,functional reactive programming,frp,functional,time-series
Author-Email: Howard Henson <howard@henson.me.uk>, Alexander Balabin <balabin@me.com>, Simon Young <whepstead@gmail.com>, Tope Olukemi <tolukemi@gmail.com>
License: MIT
Classifier: Development Status :: 3 - Alpha
Classifier: Programming Language :: Python
Classifier: Programming Language :: Python :: 3.12
Classifier: Programming Language :: Python :: Implementation :: CPython
Project-URL: Homepage, https://github.com/hhenson/hgraph
Project-URL: Documentation, https://github.com/hhenson/hgraph/blob/main/docs/index.md
Project-URL: Repository, https://github.com/hhenson/hgraph.git
Project-URL: Issues, https://github.com/hhenson/hgraph/blob/main/ISSUES.md
Project-URL: Changelog, https://github.com/hhenson/hgraph/blob/main/CHANGELOG.md
Requires-Python: <3.13,>=3.12
Requires-Dist: frozendict>=2.3.10
Requires-Dist: sortedcontainers>=2.4.0
Requires-Dist: ordered-set>=4.1.0
Requires-Dist: numpy>=1.23
Requires-Dist: polars>=1.0
Requires-Dist: sqlalchemy
Requires-Dist: duckdb
Requires-Dist: pyarrow>=16.1.0
Requires-Dist: multimethod
Requires-Dist: psutil
Requires-Dist: typing-extensions
Requires-Dist: pycurl
Requires-Dist: black>=25.1.0
Requires-Dist: pytz
Provides-Extra: web
Requires-Dist: perspective-python<4.0.0; extra == "web"
Requires-Dist: tornado; extra == "web"
Requires-Dist: requests; extra == "web"
Requires-Dist: pandas; extra == "web"
Requires-Dist: pycurl; extra == "web"
Provides-Extra: messaging
Requires-Dist: kafka-python>=2.1.5; extra == "messaging"
Provides-Extra: notebook
Requires-Dist: matplotlib; extra == "notebook"
Provides-Extra: docs
Requires-Dist: sphinx>=7.4; extra == "docs"
Requires-Dist: sphinx_rtd_theme>=2.0.0; extra == "docs"
Requires-Dist: sphinx-autodoc-typehints>=2.3.0; extra == "docs"
Requires-Dist: sphinxcontrib-plantuml>=0.30; extra == "docs"
Requires-Dist: sphinxcontrib-bibtex; extra == "docs"
Requires-Dist: pybtex-apa-style>=1.3; extra == "docs"
Requires-Dist: setuptools; extra == "docs"
Requires-Dist: myst-parser>=2.0.0; extra == "docs"
Requires-Dist: sphinxcontrib-mermaid>=0.9.0; extra == "docs"
Provides-Extra: test
Requires-Dist: pytest; extra == "test"
Requires-Dist: mypy; extra == "test"
Requires-Dist: pytest-cov; extra == "test"
Requires-Dist: coverage; extra == "test"
Requires-Dist: pytest-xdist; extra == "test"
Requires-Dist: black; extra == "test"
Provides-Extra: dev
Requires-Dist: nanobind>=2.9.2; extra == "dev"
